rhythm/__init__.py
rhythm/robot.py
rhythm/integrations/__init__.py
rhythm/integrations/email.py
rhythm/integrations/openai.py
rhythm/integrations/qdrant_db.py
rhythm/integrations/twitter.py
rhythmFramework-0.1.1.dist-info/LICENSE.txt
rhythmFramework-0.1.1.dist-info/METADATA
rhythmFramework-0.1.1.dist-info/WHEEL
rhythmFramework-0.1.1.dist-info/top_level.txt
rhythmFramework-0.1.1.dist-info/RECORD
