Metadata-Version: 2.1
Name: rhythmFramework
Version: 0.1.1
Summary: A Framework for faster development with AI Agents.
Home-page: https://www.rhyme-network.com
Author: Rhyme Network
Author-email: rhyme.ainetwork@gmail.com
License: MIT
Classifier: License :: OSI Approved :: MIT License
Classifier: Programming Language :: Python :: 3.12
Classifier: Operating System :: OS Independent
Requires-Python: >=3.12
License-File: LICENSE.txt
Requires-Dist: langchain >=0.0.350
Requires-Dist: qdrant-client >=1.7.0
Requires-Dist: tweepy >=4.14.0
Requires-Dist: openai >=1.4.0
